LICENSE.txt
README.md
setup.cfg
setup.py
pokemon_stats/__init__.py
pokemon_stats/pokemon_stats.py
pokemon_stats.egg-info/PKG-INFO
pokemon_stats.egg-info/SOURCES.txt
pokemon_stats.egg-info/dependency_links.txt
pokemon_stats.egg-info/requires.txt
pokemon_stats.egg-info/top_level.txt
test/test.py