Metadata-Version: 2.1
Name: pokemon-stats
Version: 0.1
Summary: Librería para proyecto final sobre stats de Pokémon
Home-page: https://github.com/angelachica/pokemon_stats_package
Download-URL: https://github.com/angelachica/pokemon_stats_package/archive/0.1.tar.gz
Author: Angela Chica
Author-email: angelachicaortega@gmail.com
License: MIT
Keywords: pokemon,stats,grupo
Classifier: Development Status :: 3 - Alpha
Classifier: Intended Audience :: Developers
Classifier: Topic :: Software Development :: Build Tools
Classifier: License :: OSI Approved :: MIT License
Classifier: Programming Language :: Python :: 3
Classifier: Programming Language :: Python :: 3.4
Classifier: Programming Language :: Python :: 3.5
Classifier: Programming Language :: Python :: 3.6
License-File: LICENSE.txt
